popily_api
