Metadata-Version: 1.1
Name: popily-api
Version: 0.0.6
Summary: Official Python client for the Popily API
Home-page: https://github.com/popily/popily-api
Author: Jonathon Morgan
Author-email: jonathon@popily.com
License: MIT
Download-URL: https://github.com/ushahidi/geograpy/tarball/0.0.6
Platform: UNKNOWN
